hatch_gradle_version/__init__.py
hatch_gradle_version/_hooks.py
hatch_gradle_version/py.typed
hatch_gradle_version/common/__init__.py
hatch_gradle_version/common/cd.py
hatch_gradle_version/common/codegen.py
hatch_gradle_version/common/decorators.py
hatch_gradle_version/common/gradle.py
hatch_gradle_version/common/model.py
hatch_gradle_version/common/path.py
hatch_gradle_version/common/test_gradle.py
hatch_gradle_version/plugins/__init__.py
hatch_gradle_version/plugins/version_scheme.py
hatch_gradle_version/plugins/metadata_hook/__init__.py
hatch_gradle_version/plugins/metadata_hook/base.py
hatch_gradle_version/plugins/metadata_hook/gradle_properties.py
hatch_gradle_version/plugins/metadata_hook/test_gradle_properties.py
hatch_gradle_version/plugins/metadata_hook/test_version_catalog.py
hatch_gradle_version/plugins/metadata_hook/version_catalog.py
hatch_gradle_version/plugins/version_source/__init__.py
hatch_gradle_version/plugins/version_source/base.py
hatch_gradle_version/plugins/version_source/gradle_properties.py
hatch_gradle_version/plugins/version_source/json.py
hatch_gradle_version/plugins/version_source/test_gradle_properties.py
hatch_gradle_version/plugins/version_source/test_json.py
hatch_gradle_version-0.9.12.dist-info/METADATA
hatch_gradle_version-0.9.12.dist-info/WHEEL
hatch_gradle_version-0.9.12.dist-info/entry_points.txt
hatch_gradle_version-0.9.12.dist-info/licenses/LICENSE
hatch_gradle_version-0.9.12.dist-info/RECORD
