Metadata-Version: 2.4
Name: hatch-gradle-version
Version: 0.9.12
Project-URL: Homepage, https://github.com/hexdoc-dev/hatch-gradle-version
Project-URL: Bug Tracker, https://github.com/hexdoc-dev/hatch-gradle-version/issues
Author-email: object-Object <object@objectobject.ca>
License-File: LICENSE
Classifier: Framework :: Hatch
Requires-Python: >=3.11
Requires-Dist: black==23.7.0
Requires-Dist: casefy~=0.1.7
Requires-Dist: hatchling~=1.18
Requires-Dist: jproperties~=2.1
Requires-Dist: pydantic!=2.12.0,~=2.3
Provides-Extra: dev
Requires-Dist: build; extra == 'dev'
Requires-Dist: isort==5.12.0; extra == 'dev'
Requires-Dist: pytest~=7.3; extra == 'dev'
Requires-Dist: twine; extra == 'dev'
Provides-Extra: test
Requires-Dist: pytest~=7.3; extra == 'test'
